<samplemap ID="" RRGroupAmount="2" MicPositions=";">
  <sample Root="50" LoKey="50" HiKey="50" LoVel="0" HiVel="127" RRGroup="1" FileName="{PROJECT_FOLDER}String/String4/Harmonic/600_4_nharm_03_1-2.wav" Duplicate="0" />
  <sample Root="50" LoKey="50" HiKey="50" LoVel="0" HiVel="127" RRGroup="2" FileName="{PROJECT_FOLDER}String/String4/Harmonic/600_4_nharm_03_2-2.wav" Duplicate="0" />
  <sample Root="51" LoKey="51" HiKey="51" LoVel="0" HiVel="127" RRGroup="1" FileName="{PROJECT_FOLDER}String/String4/Harmonic/600_4_nharm_05_1-2.wav" Duplicate="0" />
  <sample Root="51" LoKey="51" HiKey="51" LoVel="0" HiVel="127" RRGroup="2" FileName="{PROJECT_FOLDER}String/String4/Harmonic/600_4_nharm_05_2-2.wav" Duplicate="0" />
  <sample Root="52" LoKey="52" HiKey="52" LoVel="0" HiVel="127" RRGroup="1" FileName="{PROJECT_FOLDER}String/String4/Harmonic/600_4_nharm_07_1-2.wav" Duplicate="0" />
  <sample Root="52" LoKey="52" HiKey="52" LoVel="0" HiVel="127" RRGroup="2" FileName="{PROJECT_FOLDER}String/String4/Harmonic/600_4_nharm_07_2-2.wav" Duplicate="0" />
  <sample Root="53" LoKey="53" HiKey="53" LoVel="0" HiVel="127" RRGroup="1" FileName="{PROJECT_FOLDER}String/String4/Harmonic/600_4_nharm_09_1-2.wav" Duplicate="0" />
  <sample Root="53" LoKey="53" HiKey="53" LoVel="0" HiVel="127" RRGroup="2" FileName="{PROJECT_FOLDER}String/String4/Harmonic/600_4_nharm_09_2-2.wav" Duplicate="0" />
  <sample Root="54" LoKey="54" HiKey="54" LoVel="0" HiVel="127" RRGroup="1" FileName="{PROJECT_FOLDER}String/String4/Harmonic/600_4_nharm_12_1-2.wav" Duplicate="0" />
  <sample Root="54" LoKey="54" HiKey="54" LoVel="0" HiVel="127" RRGroup="2" FileName="{PROJECT_FOLDER}String/String4/Harmonic/600_4_nharm_12_2-2.wav" Duplicate="0" />
  <sample Root="55" LoKey="55" HiKey="55" LoVel="0" HiVel="127" RRGroup="1" FileName="{PROJECT_FOLDER}String/String4/Harmonic/600_4_nharm_19_1-2.wav" Duplicate="0" />
  <sample Root="55" LoKey="55" HiKey="55" LoVel="0" HiVel="127" RRGroup="2" FileName="{PROJECT_FOLDER}String/String4/Harmonic/600_4_nharm_19_2-2.wav" Duplicate="0" />
  <sample Root="56" LoKey="56" HiKey="56" LoVel="0" HiVel="127" RRGroup="1" FileName="{PROJECT_FOLDER}String/String4/Harmonic/600_4_nharm_sh_1-2.wav" Duplicate="0" />
  <sample Root="56" LoKey="56" HiKey="56" LoVel="0" HiVel="127" RRGroup="2" FileName="{PROJECT_FOLDER}String/String4/Harmonic/600_4_nharm_sh_2-2.wav" Duplicate="0" />
</samplemap>